dputils/.DS_Store
dputils/__init__.py
dputils/files.py
dputils/scrape.py
dputils-1.0.3.dist-info/licenses/LICENSE
dputils-1.0.3.dist-info/METADATA
dputils-1.0.3.dist-info/WHEEL
dputils-1.0.3.dist-info/RECORD
