Metadata-Version: 2.4
Name: dputils
Version: 1.0.3
Summary: This library is utility library from digipodium
License: MIT
License-File: LICENSE
Author: Team Digipodium
Maintainer: Digipodium Team
Maintainer-email: info@digipodium.com
Requires-Python: >=3.8,<4.0
Classifier: License :: OSI Approved :: MIT License
Classifier: Programming Language :: Python :: 3
Classifier: Programming Language :: Python :: 3.8
Classifier: Programming Language :: Python :: 3.9
Classifier: Programming Language :: Python :: 3.10
Classifier: Programming Language :: Python :: 3.11
Classifier: Programming Language :: Python :: 3.12
Classifier: Programming Language :: Python :: 3.13
Classifier: Programming Language :: Python :: 3.14
Requires-Dist: bs4 (>=0.0.2,<0.0.3)
Requires-Dist: docx2txt (>=0.8,<0.9)
Requires-Dist: fpdf2 (>=2.5.4,<3.0.0)
Requires-Dist: httpx[http2] (>=0.27.0,<0.28.0)
Requires-Dist: pdfminer.six (>=20220524,<20220525)
Requires-Dist: python-docx (>=1.1.2,<2.0.0)
Project-URL: Documentation, https://digipodium.github.io/dputils/
Project-URL: Homepage, https://digipodium.github.io/dputils/
Project-URL: Repository, https://github.com/digipodium/dputils
